{
 "cells": [
  {
   "cell_type": "code",
   "execution_count": 1,
   "id": "c2c1b552-d0b3-440d-ac80-d9d3bbfacafc",
   "metadata": {
    "tags": []
   },
   "outputs": [
    {
     "name": "stderr",
     "output_type": "stream",
     "text": [
      "/home/sincerely/.conda/envs/nilearn/lib/python3.7/site-packages/nilearn/__init__.py:67: FutureWarning: Python 3.7 support is deprecated and will be removed in release 0.12 of Nilearn. Consider switching to Python 3.9 or 3.10.\n",
      "  _python_deprecation_warnings()\n"
     ]
    }
   ],
   "source": [
    "import numpy as np\n",
    "import pandas as pd\n",
    "import nibabel as nib\n",
    "import os.path as op\n",
    "import matplotlib.pyplot as plt\n",
    "from glob import glob\n",
    "from nilearn.glm.first_level.hemodynamic_models import glover_hrf, glover_time_derivative\n",
    "from scipy.interpolate import interp1d\n",
    "from scipy.stats import pearsonr\n",
    "from scipy.linalg import toeplitz\n",
    "from scipy.ndimage import label\n",
    "from IPython.display import clear_output\n",
    "from time import sleep\n",
    "from numpy.linalg import inv\n",
    "\n",
    "\n",
    "### week 1, 2 ###\n",
    "def simulate_signal(onsets, conditions, TR=2, duration=None, icept=0, params_canon=None, params_tderiv=None,\n",
    "                    params_deriv1=None, phi=None, std_noise=1, osf=100, rnd_seed=None, plot=True):\n",
    "    \"\"\" Simulates a somewhat realistic voxel signal with an associated design matrix. \"\"\"\n",
    "    if rnd_seed is not None:\n",
    "        np.random.seed(rnd_seed)\n",
    "    \n",
    "    conds = sorted(np.unique(conditions))\n",
    "    P = len(conds)\n",
    "    \n",
    "    if duration is None:\n",
    "        duration = np.max(onsets) + 30\n",
    "    \n",
    "    if params_canon is None:\n",
    "        params_canon = np.zeros(P)\n",
    "\n",
    "    # TMP FIX\n",
    "    params_tderiv = params_deriv1\n",
    "    \n",
    "    if params_tderiv is None:\n",
    "        params_tderiv = np.zeros(P)\n",
    "\n",
    "    X = np.zeros((duration * osf, P))\n",
    "    for ons, con in zip(onsets, conditions):\n",
    "        X[int(ons * osf), conds.index(con)] = 1\n",
    "        \n",
    "    hrf = glover_hrf(tr=1, oversampling=osf)\n",
    "    hrf_d = glover_time_derivative(tr=1, oversampling=osf)\n",
    "\n",
    "    t_orig = np.arange(0, duration, 1 / osf)\n",
    "    t_new = np.arange(0, duration, TR)\n",
    "    \n",
    "    Xconv = np.zeros((t_orig.size, P * 2))\n",
    "    idx = 0\n",
    "    for i, this_hrf in enumerate([hrf, hrf_d]):\n",
    "        this_hrf /= this_hrf.max()\n",
    "        for ii in range(P):\n",
    "            Xconv[:, idx] = np.convolve(X[:, ii], this_hrf)[:t_orig.size]  \n",
    "            idx += 1\n",
    "    \n",
    "    Xconv = np.c_[np.ones(Xconv.shape[0]), Xconv]\n",
    "    params = np.r_[icept, params_canon, params_tderiv]\n",
    "    y = Xconv @ params\n",
    "    \n",
    "    resampler = interp1d(t_orig, y)\n",
    "    y = resampler(t_new)       \n",
    "    \n",
    "    if phi is None:\n",
    "        noise_cov = std_noise ** 2 * np.eye(y.size)\n",
    "    else:\n",
    "        noise_cov = std_noise ** 2 * phi ** toeplitz(np.arange(y.size))\n",
    "    \n",
    "    y = y + np.random.multivariate_normal(np.zeros(y.size), noise_cov)\n",
    "\n",
    "    Xconv_ds = np.zeros((t_new.size, Xconv.shape[1]))\n",
    "    for i in range(Xconv.shape[1]):\n",
    "        resampler = interp1d(t_orig, Xconv[:, i])\n",
    "        Xconv_ds[:, i] = resampler(t_new)\n",
    "    \n",
    "    est_betas = np.linalg.lstsq(Xconv_ds, y, rcond=None)[0]\n",
    "    if plot:\n",
    "        plt.figure(figsize=(15, 5))\n",
    "        plt.plot(y)\n",
    "        plt.plot(Xconv_ds @ est_betas)\n",
    "        plt.xlim(0, y.size)\n",
    "        plt.legend(['y', 'y-hat'])\n",
    "        plt.show()\n",
    "\n",
    "    return y, Xconv_ds\n",
    "\n",
    "\n",
    "\"\"\" The example_voxel_signal.npy data (from week 2) was generated as follows:\n",
    "onsets_squares = np.array([10, 110, 210, 310, 410, 510, 610, 710], dtype=int)\n",
    "onsets_circles = np.array([60, 160, 260, 360, 460, 560, 660, 760], dtype=int)\n",
    "y, X = simulate_signal(\n",
    "    np.r_[onsets_squares, onsets_circles],\n",
    "    ['squares'] * 8 + ['circles'] * 8,\n",
    "    duration=800,\n",
    "    TR=2,\n",
    "    icept=1000,\n",
    "    params_canon=[10, 7],\n",
    "    params_deriv1=[6, 0],\n",
    "    std_noise=2,\n",
    "    rnd_seed=41,\n",
    "    plot=True\n",
    ")\n",
    "np.save('example_voxel_signal.npy', y)\n",
    "\"\"\"\n",
    "\n",
    "def plot_signal_and_predicted_signal(y, X, x_lim=None, y_lim=None):\n",
    "    \"\"\" Plots a signal and its GLM prediction. \"\"\"\n",
    "    des = np.hstack((np.ones((y.size, 1)), X))\n",
    "    betas_simple = np.linalg.lstsq(des, y, rcond=None)[0]\n",
    "    plt.figure(figsize=(15, 5))\n",
    "    plt.plot(y)\n",
    "    plt.plot(des @ betas_simple, lw=2)\n",
    "    plt.xlabel('Time (in volumes)', fontsize=15)\n",
    "    plt.ylabel('Activity (A.U.)', fontsize=15)\n",
    "    \n",
    "    if x_lim is not None:\n",
    "        plt.xlim(x_lim)\n",
    "    \n",
    "    if y_lim is not None:\n",
    "        plt.ylim(y_lim)\n",
    "    \n",
    "    plt.legend(['True signal', 'Predicted signal'], loc='upper right', fontsize=15)\n",
    "    plt.title(\"Signal and predicted signal\", fontsize=25)\n",
    "    plt.grid()\n",
    "    plt.show()\n",
    "    \n",
    "    \n",
    "def plot_signal_and_predicted_signal_zoom(y, X, x_lim, y_lim, plot_params=True):\n",
    "    \"\"\" Same as previous function, but zoomed in. \"\"\"\n",
    "    des = np.hstack((np.ones((y.size, 1)), X))\n",
    "    betas_simple = np.linalg.lstsq(des, y, rcond=None)[0]\n",
    "    yhat = des @ betas_simple\n",
    "    plt.figure(figsize=(15, 5))\n",
    "    plt.plot(y)\n",
    "    plt.plot(yhat, lw=2)\n",
    "    plt.xlim(x_lim)\n",
    "    plt.ylim(y_lim)\n",
    "    plt.xlabel('Time (in volumes)', fontsize=20)\n",
    "    plt.ylabel('Activity (A.U.)', fontsize=20)\n",
    "    \n",
    "    if plot_params:\n",
    "        xmid = (x_lim[1] + x_lim[0]) // 2\n",
    "        plt.text(xmid, y_lim[0] + (betas_simple[0] - y_lim[0]) // 2, r\"$\\hat{\\beta}_{intercept}$\", fontsize=15)\n",
    "        plt.arrow(xmid, y_lim[0], 0, betas_simple[0] - y_lim[0], head_width=0.3,\n",
    "                  length_includes_head=True, color='k')\n",
    "\n",
    "        for t in np.where(yhat[x_lim[0]:x_lim[1]] == yhat.max())[0]:\n",
    "            t += x_lim[0]\n",
    "            plt.arrow(t, betas_simple[0], 0, betas_simple[1], head_width=0.3,\n",
    "                      length_includes_head=True, color='k')\n",
    "            plt.text(t, betas_simple[0] + betas_simple[1], r\"$\\hat{\\beta}_{1}$\", fontsize=15, ha='center')\n",
    "        \n",
    "    plt.legend(['True signal', 'Predicted signal'], fontsize=15, loc='upper right')\n",
    "    plt.show()\n",
    "\n",
    "\n",
    "### week 3 ###\n",
    "def calculate_stats_for_iq_income_dataset(iq_income_data, which='lowvar'):\n",
    "    \n",
    "    if which == 'lowvar':\n",
    "        X, y = iq_income_data['X_lv'], iq_income_data['y_lv']\n",
    "    else:\n",
    "        X, y = iq_income_data['X_hv'], iq_income_data['y_hv']\n",
    "        \n",
    "    contrast = np.array([0, 1])\n",
    "    beta = np.linalg.lstsq(X, y, rcond=None)[0]\n",
    "    y_hat = X.dot(beta)\n",
    "    mse = ((y - y_hat) ** 2).mean()\n",
    "    des_var = contrast.dot(np.linalg.pinv(X.T.dot(X))).dot(contrast.T)\n",
    "    sse_df = ((y - y_hat) ** 2).sum() / (X.shape[0] - X.shape[1])\n",
    "    se = np.sqrt(sse_df * des_var)\n",
    "    tval = contrast.dot(beta) / se\n",
    "    return beta, mse, tval\n",
    "\n",
    "\n",
    "def calc_eff(N, X, c):\n",
    "    X = np.hstack((np.ones((N, 1)), X))\n",
    "    dvar = []\n",
    "    for i in range(c.shape[0]):\n",
    "        dvar.append(c[i, :].dot(np.linalg.pinv(X.T.dot(X))).dot(c[i, :].T))\n",
    "    eff = c.shape[0] / sum(dvar)\n",
    "\n",
    "    return eff, X\n",
    "\n",
    "\n",
    "### week 4 ###\n",
    "from scipy.ndimage import affine_transform\n",
    "from numpy.linalg import inv\n",
    "\n",
    "\n",
    "def create_sine_wave(timepoints, frequency=1,amplitude=1, phase=0):\n",
    "    return amplitude * np.sin(2 * np.pi * frequency * timepoints + phase)\n",
    "\n",
    "\n",
    "def add_motion_to_vols(vols):\n",
    "    \n",
    "    new_vols = np.zeros_like(vols)\n",
    "    for i in range(new_vols.shape[-1]):\n",
    "        rot = np.random.uniform(-2, 2, 3)\n",
    "        trans = np.random.uniform(-0.1, 0.1, 3)\n",
    "        rot_mat = get_rotation_matrix(*rot)\n",
    "        trans_mat = get_translation_matrix(*trans)\n",
    "        center = np.eye(4)\n",
    "        center[:, -1] = np.r_[np.array(vols.shape[:3]) // 2 - 0.5, 1]\n",
    "        affine = trans_mat @ center @ rot_mat @ inv(center)\n",
    "        new_vols[:, :, :, i] = affine_transform(vols[:, :, :, i], matrix=inv(affine))\n",
    "    return new_vols\n",
    "\n",
    "\n",
    "def animate_volumes(vols, idx=25, axis=2, show_until=None, to_sleep=0.5, **kwargs):\n",
    "    if show_until is None:\n",
    "        show_until = vols.shape[-1]\n",
    "    \n",
    "    vols = np.take(vols, idx, axis)\n",
    "    for i in range(show_until):\n",
    "        plt.figure(figsize=(8, 8))\n",
    "        plt.imshow(vols[:, :, i], cmap='gray', **kwargs)\n",
    "        plt.title(\"Volume nr. %i\" % i, fontsize=(25))\n",
    "        plt.axis('off')\n",
    "        plt.show()\n",
    "        sleep(to_sleep)\n",
    "        clear_output(wait=True)\n",
    "\n",
    "\n",
    "def get_rotation_matrix(x=0, y=0, z=0):\n",
    "    \"\"\" Computes the rotation matrix.\n",
    "    \n",
    "    Parameters\n",
    "    ----------\n",
    "    x : float\n",
    "        Rotation in the x (first) dimension in degrees\n",
    "    y : float\n",
    "        Rotation in the y (second) dimension in degrees\n",
    "    z : float\n",
    "        Rotation in the z (third) dimension in degrees\n",
    "    \n",
    "    Returns\n",
    "    -------\n",
    "    rot_mat : numpy ndarray\n",
    "        Numpy array of shape 4 x 4\n",
    "    \"\"\"\n",
    "    \n",
    "    x = np.deg2rad(x)\n",
    "    y = np.deg2rad(y)\n",
    "    z = np.deg2rad(z)\n",
    "    \n",
    "    rot_roll = np.array([\n",
    "        [1, 0, 0, 0],\n",
    "        [0, np.cos(x), -np.sin(x), 0],\n",
    "        [0, np.sin(x), np.cos(x), 0],\n",
    "        [0, 0, 0, 1]\n",
    "    ])\n",
    "\n",
    "    rot_pitch = np.array([\n",
    "        [np.cos(y), 0, np.sin(y), 0],\n",
    "        [0, 1, 0, 0],\n",
    "        [-np.sin(y), 0, np.cos(y), 0],\n",
    "        [0, 0, 0, 1]\n",
    "    ])\n",
    "\n",
    "    rot_yaw = np.array([\n",
    "        [np.cos(z), -np.sin(z), 0, 0],\n",
    "        [np.sin(z), np.cos(z), 0, 0],\n",
    "        [0, 0, 1, 0],\n",
    "        [0, 0, 0, 1]\n",
    "    ])\n",
    "\n",
    "    rot_mat = rot_roll @ rot_pitch @ rot_yaw\n",
    "    return rot_mat\n",
    "\n",
    "\n",
    "def get_translation_matrix(x=0, y=0, z=0):\n",
    "    \"\"\" Computes the translation matrix.\n",
    "    \n",
    "    Parameters\n",
    "    ----------\n",
    "    x : float\n",
    "        Translation in the x (first) dimension in voxels\n",
    "    y : float\n",
    "        Rotation in the y (second) dimension in voxels\n",
    "    z : float\n",
    "        Rotation in the z (third) dimension in voxels\n",
    "    \n",
    "    Returns\n",
    "    -------\n",
    "    trans_mat : numpy ndarray\n",
    "        Numpy array of shape 4 x 4\n",
    "    \"\"\"\n",
    "    \n",
    "    trans_mat = np.eye(4)\n",
    "    trans_mat[:, -1] = [x, y, z, 1]\n",
    "    return trans_mat\n",
    "\n",
    "\n",
    "### NOTE SPIKE PRED\n",
    "\"\"\"\n",
    "pred = np.zeros(500)\n",
    "pred[::50] = 1\n",
    "hrf = glover_hrf(tr=1, oversampling=1)\n",
    "pred = np.convolve(pred, hrf)[:pred.size, np.newaxis]\n",
    "spike_sig = pred.squeeze() + np.random.normal(1000, 0.2, pred.size)\n",
    "all_sig = np.random.normal(0, 0.1, size=pred.size) + np.random.normal(1000, 0.2, ((10, 10, 10, pred.size)))\n",
    "all_sig[5, 5, 5, :] = spike_sig\n",
    "all_sig[:, :, :, 99] += 0.4\n",
    "all_sig[:, :, :, 100] -= 0.4\n",
    "all_sig[:, :, :, 299] += 0.4\n",
    "all_sig[:, :, :, 300] -= 0.4\n",
    "rmssd = np.sqrt(np.mean((all_sig[:, :, :, 1:] - np.diff(all_sig, axis=-1)) ** 2, axis=(0, 1, 2)))\n",
    "np.savez('spike_data.npz', all_sig=all_sig, pred=pred)\n",
    "\"\"\"\n",
    "\n",
    "### For posterity\n",
    "def resample2_image(image, trans_mat, rot_mat):\n",
    "    \"\"\" Resamples an image given a translation and rotation matrix.\n",
    "    \n",
    "    Parameters\n",
    "    ----------\n",
    "    image : numpy array\n",
    "        A 3D numpy array with image data\n",
    "    trans_mat : numpy array\n",
    "        A numpy array of shape 4 x 4\n",
    "    rot_mat : numpy array\n",
    "        A numpy array of shape 4 x 4\n",
    "    \n",
    "    Returns\n",
    "    -------\n",
    "    image_reg : numpy array\n",
    "        A transformed 3D numpy array\n",
    "    \"\"\"\n",
    "    \n",
    "    # We need to rotate around the origin, not (0, 0), so\n",
    "    # add a \"center\" translation\n",
    "    center = np.eye(4)\n",
    "    center[:3, -1] = np.array(image.shape) // 2 - 0.5\n",
    "    A = center @ rot_mat @ trans_mat @ inv(center)\n",
    "    ### WHYYYYY do I have to switch rot and trans here?\n",
    "    \n",
    "    # affine_transform does \"pull\" resampling by default, so\n",
    "    # we need the inverse of A\n",
    "    image_corr = affine_transform(image, matrix=np.linalg.inv(A))\n",
    "    \n",
    "    return image_corr\n",
    "\n",
    "\"\"\" How the signal (y) for the last todo of week 4 was made\n",
    "motion_params = np.loadtxt('func_motion_pars.txt')\n",
    "N = motion_params.shape[0]\n",
    "pred = np.zeros(N)\n",
    "onsets = np.arange(0, N, 40)\n",
    "pred[onsets.astype(int)] = 1\n",
    "hrf = glover_hrf(tr=1, oversampling=1)\n",
    "hrf /= hrf.max()\n",
    "pred = np.convolve(pred, hrf)[:N]\n",
    "motion_params[:, -1] += (pred * 0.1)\n",
    "motion_params[:, -2] -= (pred * 0.1)\n",
    "betas = np.concatenate((np.array([1000, 5]), np.random.uniform(-2, 2, 6)))\n",
    "X = np.c_[np.ones(N), pred, motion_params]\n",
    "y = X @ betas + np.random.normal(0, 5, size=N)\n",
    "np.savetxt('func_motion_pars_new.txt', motion_params)\n",
    "np.savez('data_motion_filtering.npz', X=np.c_[np.ones(pred.size), pred], sig=y)\n",
    "\"\"\"\n",
    "\n",
    "def compute_tvalue(X, y, c):\n",
    "    # Hardcode some things to make sure it doesn't work for other data\n",
    "    b = inv(X.T @ X) @ X.T @ y\n",
    "    sigmasq = np.sum((y - X @ b) ** 2) / (40 - 2)\n",
    "    dv = c @ inv(X.T @ X) @ c.T\n",
    "    tvalue = (c @ b) / np.sqrt(sigmasq * dv)\n",
    "    return tvalue\n",
    "\n",
    "\n",
    "def rft_cluster_threshold(data, z_thresh=3, p_clust=0.05):\n",
    "    \"\"\" This function implements a form of cluster-based\n",
    "    RFT thresholding. It is based on a non-parametric\n",
    "    simulation of cluster sizes under the null (with a \n",
    "    given smoothness and data shape).\n",
    "    \n",
    "    Do not use this for your own analyses. Only works for\n",
    "    the exact data (smoothness) of the simulation data from\n",
    "    week 6.\n",
    "    \"\"\"\n",
    "    \n",
    "    clust = np.load('clust_size_dist_data.npz')\n",
    "    ms, zx = clust['dist'], clust['zx']\n",
    "\n",
    "    z_idx = np.abs(zx - z_thresh).argmin()\n",
    "    mask = np.zeros(data.shape, dtype=bool)\n",
    "    clustered = label(data > z_thresh)[0]\n",
    "    cluster_ids = np.unique(clustered)[1:]\n",
    "    for cid in cluster_ids:\n",
    "        clust_idx = clustered == cid\n",
    "        c_size = np.sum(clust_idx)\n",
    "        pval = (np.sum(ms[:, z_idx] > c_size) + 1) / (ms.shape[0] + 1)\n",
    "        if pval <= p_clust:\n",
    "            mask[clust_idx] = True\n",
    "            \n",
    "    return mask\n",
    "\n",
    "\n",
    "def create_fsl_onset_files(data_dir):\n",
    "    \"\"\" Creates FSL-style onset files (tab-delimited, without headers). \"\"\"\n",
    "    subs = sorted(glob(op.join(data_dir, 'sub-03')))\n",
    "    for sub in subs:\n",
    "        # first flocBLOCKED and flocER files\n",
    "        flocs = sorted(glob(op.join(sub, 'ses-*', 'func', '*floc*_events.tsv')))\n",
    "\n",
    "        for floc in flocs:\n",
    "            df = pd.read_csv(floc, sep='\\t')\n",
    "            conds = np.unique(df['trial_type'])\n",
    "            for con in conds:\n",
    "                f_out = floc.replace('_events.tsv', f'_condition-{con}_events.txt')\n",
    "                #if op.isfile(f_out):\n",
    "                #    continue\n",
    "\n",
    "                tmp = df.query(\"trial_type == @con\").copy()\n",
    "                tmp.loc[:, 'weight'] = 1\n",
    "                tmp.loc[:, 'duration'] = tmp.loc[:, 'duration'].round(1)\n",
    "                tmp = tmp.loc[:, ['onset', 'duration', 'weight']]  # reorder\n",
    "                tmp.to_csv(f_out, header=False, index=False, sep='\\t')"
   ]
  },
  {
   "cell_type": "code",
   "execution_count": 12,
   "id": "b6d9083e-79ab-47be-85bb-500963f0af60",
   "metadata": {
    "tags": []
   },
   "outputs": [
    {
     "name": "stdout",
     "output_type": "stream",
     "text": [
      "          0 STORE_GLOBAL            13 (13)\n",
      "          2 <13>\n",
      "    >>    4 <0>\n",
      "          6 <0>\n",
      "    >>    8 <208>                  217\n",
      "    >>   10 <34>\n",
      "         12 <229>                   21\n",
      "    >>   14 <0>\n",
      "    >>   16 <227>                    0\n",
      "         18 <0>\n",
      "    >>   20 <0>\n",
      "         22 <0>\n",
      "    >>   24 <0>\n",
      "         26 <0>\n",
      "    >>   28 <0>\n",
      "         30 <0>\n",
      "    >>   32 <0>\n",
      "    >>   34 <0>\n",
      "    >>   36 <0>\n",
      "    >>   38 <0>\n",
      "    >>   40 <0>\n",
      "         42 <176>                    0\n",
      "         44 <0>\n",
      "    >>   46 LOAD_CONST               0 (0)\n",
      "    >>   48 LOAD_CONST               1 (1)\n",
      "    >>   50 IMPORT_NAME              0 (0)\n",
      "    >>   52 STORE_NAME               1 (1)\n",
      "    >>   54 LOAD_CONST               0 (0)\n",
      "         56 LOAD_CONST               2 (2)\n",
      "    >>   58 IMPORT_NAME              2 (2)\n",
      "         60 IMPORT_FROM              3 (3)\n",
      "    >>   62 STORE_NAME               3 (3)\n",
      "    >>   64 POP_TOP\n",
      "    >>   66 LOAD_CONST               0 (0)\n",
      "         68 LOAD_CONST               3 (3)\n",
      "         70 IMPORT_NAME              4 (4)\n",
      "    >>   72 IMPORT_FROM              5 (5)\n",
      "         74 STORE_NAME               5 (5)\n",
      "    >>   76 POP_TOP\n",
      "         78 LOAD_CONST               0 (0)\n",
      "         80 LOAD_CONST               4 (4)\n",
      "         82 IMPORT_NAME              6 (6)\n",
      "    >>   84 IMPORT_FROM              7 (7)\n",
      "         86 STORE_NAME               7 (7)\n",
      "         88 POP_TOP\n",
      "    >>   90 LOAD_CONST               5 (5)\n",
      "         92 LOAD_CONST               6 (6)\n",
      "         94 MAKE_FUNCTION            0\n",
      "         96 STORE_NAME               8 (8)\n",
      "         98 LOAD_CONST               7 (7)\n",
      "    >>  100 LOAD_CONST               8 (8)\n",
      "    >>  102 MAKE_FUNCTION            0\n",
      "        104 STORE_NAME               9 (9)\n",
      "    >>  106 LOAD_CONST              38 (38)\n",
      "    >>  108 LOAD_CONST              10 (10)\n",
      "    >>  110 LOAD_CONST              11 (11)\n",
      "    >>  112 MAKE_FUNCTION            1\n",
      "    >>  114 STORE_NAME              10 (10)\n",
      "    >>  116 LOAD_CONST              12 (12)\n",
      "    >>  118 LOAD_CONST              13 (13)\n",
      "        120 MAKE_FUNCTION            0\n",
      "        122 STORE_NAME              11 (11)\n",
      "        124 LOAD_CONST              39 (39)\n",
      "        126 LOAD_CONST              15 (15)\n",
      "        128 LOAD_CONST              16 (16)\n",
      "    >>  130 MAKE_FUNCTION            1\n",
      "        132 STORE_NAME              12 (12)\n",
      "    >>  134 LOAD_CONST              17 (17)\n",
      "        136 LOAD_CONST              18 (18)\n",
      "        138 MAKE_FUNCTION            0\n",
      "        140 STORE_NAME              13 (13)\n",
      "        142 LOAD_CONST              19 (19)\n",
      "        144 LOAD_CONST              20 (20)\n",
      "        146 MAKE_FUNCTION            0\n",
      "        148 STORE_NAME              14 (14)\n",
      "        150 LOAD_CONST              21 (21)\n",
      "        152 LOAD_CONST              22 (22)\n",
      "        154 MAKE_FUNCTION            0\n",
      "        156 STORE_NAME              15 (15)\n",
      "        158 LOAD_CONST              40 (40)\n",
      "        160 LOAD_CONST              24 (24)\n",
      "        162 LOAD_CONST              25 (25)\n",
      "        164 MAKE_FUNCTION            1\n",
      "        166 STORE_NAME              16 (16)\n",
      "        168 LOAD_CONST              41 (41)\n",
      "        170 LOAD_CONST              26 (26)\n",
      "        172 LOAD_CONST              27 (27)\n",
      "        174 MAKE_FUNCTION            1\n",
      "        176 STORE_NAME              17 (17)\n",
      "    >>  178 LOAD_CONST              28 (28)\n",
      "        180 LOAD_CONST              29 (29)\n",
      "        182 MAKE_FUNCTION            0\n",
      "    >>  184 STORE_NAME              18 (18)\n",
      "        186 LOAD_CONST              30 (30)\n",
      "        188 LOAD_CONST              31 (31)\n",
      "        190 MAKE_FUNCTION            0\n",
      "        192 STORE_NAME              19 (19)\n",
      "        194 LOAD_CONST              32 (32)\n",
      "        196 LOAD_CONST              33 (33)\n",
      "        198 MAKE_FUNCTION            0\n",
      "        200 STORE_NAME              20 (20)\n",
      "        202 LOAD_CONST              34 (34)\n",
      "        204 LOAD_CONST              35 (35)\n",
      "        206 MAKE_FUNCTION            0\n",
      "        208 STORE_NAME              21 (21)\n",
      "        210 LOAD_CONST              36 (36)\n",
      "        212 LOAD_CONST              37 (37)\n",
      "        214 MAKE_FUNCTION            0\n",
      "        216 STORE_NAME              22 (22)\n",
      "        218 LOAD_CONST               1 (1)\n",
      "        220 RETURN_VALUE\n",
      "        222 <41>\n",
      "        224 <233>                    0\n",
      "        226 <0>\n",
      "        228 <0>\n",
      "        230 <41>\n",
      "        232 <218>                    8\n",
      "        234 BUILD_MAP              110\n",
      "        236 LOAD_GLOBAL            101 (101)\n",
      "        238 POP_JUMP_IF_FALSE      112\n",
      "        240 <49>\n",
      "        242 <41>\n",
      "        244 <218>                    3\n",
      "        246 BUILD_MAP              110\n",
      "        248 <118>                   41\n",
      "        250 POP_TOP\n",
      "        252 UNARY_INVERT\n",
      "        254 STORE_GLOBAL           117 (117)\n",
      "        256 POP_JUMP_IF_TRUE       115\n",
      "        258 BUILD_MAP               97\n",
      "        260 JUMP_FORWARD            95 (to 357)\n",
      "        262 BUILD_TUPLE            105\n",
      "        264 IMPORT_NAME            116 (116)\n",
      "        266 LOAD_NAME              114 (114)\n",
      "        268 <99>                     2\n",
      "        270 <0>\n",
      "        272 <0>\n",
      "        274 <0>\n",
      "        276 <0>\n",
      "        278 <0>\n",
      "        280 <0>\n",
      "        282 <0>\n",
      "        284 <0>\n",
      "        286 <0>\n",
      "        288 <0>\n",
      "        290 <0>\n",
      "        292 <0>\n",
      "        294 <194>                    0\n",
      "        296 <0>\n",
      "        298 LOAD_CONST               1 (1)\n",
      "        300 STORE_FAST               2 (2)\n",
      "        302 LOAD_FAST                0 (0)\n",
      "        304 LOAD_ATTR                0 (0)\n",
      "        306 UNPACK_SEQUENCE          2\n",
      "        308 STORE_FAST               3 (3)\n",
      "        310 STORE_FAST               4 (4)\n",
      "        312 LOAD_FAST                2 (2)\n",
      "        314 LOAD_FAST                3 (3)\n",
      "        316 BINARY_MULTIPLY\n",
      "        318 STORE_FAST               5 (5)\n",
      "        320 LOAD_FAST                2 (2)\n",
      "        322 LOAD_FAST                4 (4)\n",
      "        324 BINARY_TRUE_DIVIDE\n",
      "        326 STORE_FAST               6 (6)\n",
      "        328 LOAD_GLOBAL              1 (1)\n",
      "        330 LOAD_ATTR                2 (2)\n",
      "        332 LOAD_FAST                6 (6)\n",
      "        334 LOAD_CONST               2 (2)\n",
      "        336 BINARY_MULTIPLY\n",
      "        338 LOAD_FAST                5 (5)\n",
      "        340 LOAD_FAST                6 (6)\n",
      "        342 LOAD_CONST               2 (2)\n",
      "        344 BINARY_MULTIPLY\n",
      "        346 BINARY_ADD\n",
      "        348 LOAD_FAST                3 (3)\n",
      "        350 LOAD_CONST               3 (3)\n",
      "        352 LOAD_CONST               4 (4)\n",
      "        354 CALL_FUNCTION_KW         4\n",
      "        356 STORE_FAST               7 (7)\n",
      "        358 LOAD_GLOBAL              1 (1)\n",
      "        360 LOAD_METHOD              3 (3)\n",
      "        362 LOAD_FAST                0 (0)\n",
      "        364 CALL_METHOD              1\n",
      "        366 STORE_FAST               8 (8)\n",
      "        368 LOAD_GLOBAL              4 (4)\n",
      "        370 LOAD_FAST                8 (8)\n",
      "        372 LOAD_ATTR                0 (0)\n",
      "        374 LOAD_CONST               5 (5)\n",
      "        376 BINARY_SUBSCR\n",
      "        378 CALL_FUNCTION            1\n",
      "        380 GET_ITER\n",
      "        382 FOR_ITER                82 (to 466)\n",
      "        384 STORE_FAST               9 (9)\n",
      "        386 LOAD_GLOBAL              1 (1)\n",
      "        388 LOAD_ATTR                2 (2)\n",
      "        390 LOAD_FAST                6 (6)\n",
      "        392 LOAD_FAST                9 (9)\n",
      "        394 BINARY_MULTIPLY\n",
      "        396 LOAD_FAST                5 (5)\n",
      "        398 LOAD_FAST                6 (6)\n",
      "        400 LOAD_FAST                9 (9)\n",
      "        402 BINARY_MULTIPLY\n",
      "        404 BINARY_ADD\n",
      "        406 LOAD_FAST                3 (3)\n",
      "        408 LOAD_CONST               3 (3)\n",
      "        410 LOAD_CONST               4 (4)\n",
      "        412 CALL_FUNCTION_KW         4\n",
      "        414 STORE_FAST              10 (10)\n",
      "        416 LOAD_GLOBAL              5 (5)\n",
      "        418 LOAD_FAST               10 (10)\n",
      "        420 LOAD_FAST                0 (0)\n",
      "        422 LOAD_CONST               0 (0)\n",
      "        424 LOAD_CONST               0 (0)\n",
      "        426 BUILD_SLICE              2\n",
      "        428 LOAD_FAST                9 (9)\n",
      "        430 BUILD_TUPLE              2\n",
      "        432 BINARY_SUBSCR\n",
      "        434 LOAD_CONST               6 (6)\n",
      "        436 LOAD_CONST               7 (7)\n",
      "        438 LOAD_CONST               8 (8)\n",
      "        440 CALL_FUNCTION_KW         4\n",
      "        442 STORE_FAST              11 (11)\n",
      "        444 LOAD_FAST               11 (11)\n",
      "        446 LOAD_FAST                7 (7)\n",
      "        448 CALL_FUNCTION            1\n",
      "        450 LOAD_FAST                8 (8)\n",
      "        452 LOAD_CONST               0 (0)\n",
      "        454 LOAD_CONST               0 (0)\n",
      "        456 BUILD_SLICE              2\n",
      "        458 LOAD_FAST                9 (9)\n",
      "        460 BUILD_TUPLE              2\n",
      "        462 STORE_SUBSCR\n",
      "        464 JUMP_ABSOLUTE           84\n",
      "    >>  466 LOAD_GLOBAL              1 (1)\n",
      "        468 LOAD_ATTR                6 (6)\n",
      "        470 LOAD_METHOD              7 (7)\n",
      "        472 LOAD_FAST                8 (8)\n",
      "        474 LOAD_FAST                1 (1)\n",
      "        476 CALL_METHOD              2\n",
      "        478 POP_TOP\n",
      "        480 LOAD_GLOBAL              8 (8)\n",
      "        482 LOAD_CONST               9 (9)\n",
      "        484 CALL_FUNCTION            1\n",
      "        486 POP_TOP\n",
      "        488 LOAD_CONST               0 (0)\n",
      "        490 RETURN_VALUE\n",
      "        492 <41>\n",
      "        494 INPLACE_XOR\n",
      "        496 ROT_THREE\n",
      "        498 <0>\n",
      "        500 <233>                   15\n",
      "        502 <0>\n",
      "        504 <0>\n",
      "        506 <41>\n",
      "        508 STORE_NAME               8 (8)\n",
      "        510 LOAD_NAME              110 (110)\n",
      "        512 LOAD_CONST             112 (112)\n",
      "        514 JUMP_IF_FALSE_OR_POP   105\n",
      "        516 JUMP_FORWARD           116 (to 634)\n",
      "        518 <233>                    1\n",
      "        520 <0>\n",
      "        522 <0>\n",
      "        524 UNARY_NEGATIVE\n",
      "        526 SETUP_LOOP             116 (to 644)\n",
      "        528 POP_JUMP_IF_FALSE       97\n",
      "        530 JUMP_IF_TRUE_OR_POP    111\n",
      "        532 IMPORT_NAME             97 (97)\n",
      "        534 LOAD_GLOBAL            101 (101)\n",
      "        536 STORE_NAME               5 (5)\n",
      "        538 <99>                   117\n",
      "        540 DELETE_GLOBAL          105 (105)\n",
      "        542 <99>                    41\n",
      "        544 ROT_TWO\n",
      "        546 UNARY_POSITIVE\n",
      "        548 BUILD_MAP              108\n",
      "        550 IMPORT_NAME             95 (95)\n",
      "        552 <118>                   97\n",
      "        554 IMPORT_NAME            117 (117)\n",
      "        556 LOAD_NAME              218 (218)\n",
      "        558 DUP_TOP\n",
      "        560 BUILD_MAP              110\n",
      "        562 LOAD_CONST             250 (250)\n",
      "        564 UNARY_POSITIVE\n",
      "        566 LOAD_NAME              108 (108)\n",
      "        568 IMPORT_NAME             32 (32)\n",
      "        570 LOAD_CONST             111 (111)\n",
      "        572 JUMP_FORWARD           101 (to 675)\n",
      "        574 <33>\n",
      "        576 NOP\n",
      "        578 DUP_TOP_TWO\n",
      "        580 BUILD_SET               97\n",
      "        582 JUMP_IF_TRUE_OR_POP    101\n",
      "        584 <218>                    2\n",
      "        586 JUMP_FORWARD           112 (to 700)\n",
      "        588 STORE_NAME               8 (8)\n",
      "        590 IMPORT_NAME            105 (105)\n",
      "        592 JUMP_FORWARD           115 (to 709)\n",
      "        594 JUMP_IF_TRUE_OR_POP     97\n",
      "        596 <99>                   101\n",
      "        598 STORE_NAME              10 (10)\n",
      "        600 SETUP_FINALLY          101 (to 703)\n",
      "        602 POP_JUMP_IF_FALSE      111\n",
      "        604 POP_JUMP_IF_TRUE        95\n",
      "        606 IMPORT_NAME            105 (105)\n"
     ]
    },
    {
     "ename": "IndexError",
     "evalue": "tuple index out of range",
     "output_type": "error",
     "traceback": [
      "\u001b[0;31m---------------------------------------------------------------------------\u001b[0m",
      "\u001b[0;31mIndexError\u001b[0m                                Traceback (most recent call last)",
      "\u001b[0;32m/tmp/ipykernel_11824/3613766634.py\u001b[0m in \u001b[0;36m<module>\u001b[0;34m\u001b[0m\n\u001b[1;32m     10\u001b[0m     \u001b[0mcode_object\u001b[0m \u001b[0;34m=\u001b[0m \u001b[0mfile\u001b[0m\u001b[0;34m.\u001b[0m\u001b[0mread\u001b[0m\u001b[0;34m(\u001b[0m\u001b[0;34m)\u001b[0m  \u001b[0;31m# Read the bytecode from the file\u001b[0m\u001b[0;34m\u001b[0m\u001b[0;34m\u001b[0m\u001b[0m\n\u001b[1;32m     11\u001b[0m \u001b[0;34m\u001b[0m\u001b[0m\n\u001b[0;32m---> 12\u001b[0;31m \u001b[0mdis\u001b[0m\u001b[0;34m.\u001b[0m\u001b[0mdis\u001b[0m\u001b[0;34m(\u001b[0m\u001b[0mcode_object\u001b[0m\u001b[0;34m)\u001b[0m\u001b[0;34m\u001b[0m\u001b[0;34m\u001b[0m\u001b[0m\n\u001b[0m",
      "\u001b[0;32m~/.conda/envs/nilearn/lib/python3.7/dis.py\u001b[0m in \u001b[0;36mdis\u001b[0;34m(x, file, depth)\u001b[0m\n\u001b[1;32m     70\u001b[0m         \u001b[0m_disassemble_recursive\u001b[0m\u001b[0;34m(\u001b[0m\u001b[0mx\u001b[0m\u001b[0;34m,\u001b[0m \u001b[0mfile\u001b[0m\u001b[0;34m=\u001b[0m\u001b[0mfile\u001b[0m\u001b[0;34m,\u001b[0m \u001b[0mdepth\u001b[0m\u001b[0;34m=\u001b[0m\u001b[0mdepth\u001b[0m\u001b[0;34m)\u001b[0m\u001b[0;34m\u001b[0m\u001b[0;34m\u001b[0m\u001b[0m\n\u001b[1;32m     71\u001b[0m     \u001b[0;32melif\u001b[0m \u001b[0misinstance\u001b[0m\u001b[0;34m(\u001b[0m\u001b[0mx\u001b[0m\u001b[0;34m,\u001b[0m \u001b[0;34m(\u001b[0m\u001b[0mbytes\u001b[0m\u001b[0;34m,\u001b[0m \u001b[0mbytearray\u001b[0m\u001b[0;34m)\u001b[0m\u001b[0;34m)\u001b[0m\u001b[0;34m:\u001b[0m \u001b[0;31m# Raw bytecode\u001b[0m\u001b[0;34m\u001b[0m\u001b[0;34m\u001b[0m\u001b[0m\n\u001b[0;32m---> 72\u001b[0;31m         \u001b[0m_disassemble_bytes\u001b[0m\u001b[0;34m(\u001b[0m\u001b[0mx\u001b[0m\u001b[0;34m,\u001b[0m \u001b[0mfile\u001b[0m\u001b[0;34m=\u001b[0m\u001b[0mfile\u001b[0m\u001b[0;34m)\u001b[0m\u001b[0;34m\u001b[0m\u001b[0;34m\u001b[0m\u001b[0m\n\u001b[0m\u001b[1;32m     73\u001b[0m     \u001b[0;32melif\u001b[0m \u001b[0misinstance\u001b[0m\u001b[0;34m(\u001b[0m\u001b[0mx\u001b[0m\u001b[0;34m,\u001b[0m \u001b[0mstr\u001b[0m\u001b[0;34m)\u001b[0m\u001b[0;34m:\u001b[0m    \u001b[0;31m# Source code\u001b[0m\u001b[0;34m\u001b[0m\u001b[0;34m\u001b[0m\u001b[0m\n\u001b[1;32m     74\u001b[0m         \u001b[0m_disassemble_str\u001b[0m\u001b[0;34m(\u001b[0m\u001b[0mx\u001b[0m\u001b[0;34m,\u001b[0m \u001b[0mfile\u001b[0m\u001b[0;34m=\u001b[0m\u001b[0mfile\u001b[0m\u001b[0;34m,\u001b[0m \u001b[0mdepth\u001b[0m\u001b[0;34m=\u001b[0m\u001b[0mdepth\u001b[0m\u001b[0;34m)\u001b[0m\u001b[0;34m\u001b[0m\u001b[0;34m\u001b[0m\u001b[0m\n",
      "\u001b[0;32m~/.conda/envs/nilearn/lib/python3.7/dis.py\u001b[0m in \u001b[0;36m_disassemble_bytes\u001b[0;34m(code, lasti, varnames, names, constants, cells, linestarts, file, line_offset)\u001b[0m\n\u001b[1;32m    388\u001b[0m     for instr in _get_instructions_bytes(code, varnames, names,\n\u001b[1;32m    389\u001b[0m                                          \u001b[0mconstants\u001b[0m\u001b[0;34m,\u001b[0m \u001b[0mcells\u001b[0m\u001b[0;34m,\u001b[0m \u001b[0mlinestarts\u001b[0m\u001b[0;34m,\u001b[0m\u001b[0;34m\u001b[0m\u001b[0;34m\u001b[0m\u001b[0m\n\u001b[0;32m--> 390\u001b[0;31m                                          line_offset=line_offset):\n\u001b[0m\u001b[1;32m    391\u001b[0m         new_source_line = (show_lineno and\n\u001b[1;32m    392\u001b[0m                            \u001b[0minstr\u001b[0m\u001b[0;34m.\u001b[0m\u001b[0mstarts_line\u001b[0m \u001b[0;32mis\u001b[0m \u001b[0;32mnot\u001b[0m \u001b[0;32mNone\u001b[0m \u001b[0;32mand\u001b[0m\u001b[0;34m\u001b[0m\u001b[0;34m\u001b[0m\u001b[0m\n",
      "\u001b[0;32m~/.conda/envs/nilearn/lib/python3.7/dis.py\u001b[0m in \u001b[0;36m_get_instructions_bytes\u001b[0;34m(code, varnames, names, constants, cells, linestarts, line_offset)\u001b[0m\n\u001b[1;32m    335\u001b[0m                 \u001b[0margval\u001b[0m\u001b[0;34m,\u001b[0m \u001b[0margrepr\u001b[0m \u001b[0;34m=\u001b[0m \u001b[0m_get_name_info\u001b[0m\u001b[0;34m(\u001b[0m\u001b[0marg\u001b[0m\u001b[0;34m,\u001b[0m \u001b[0mvarnames\u001b[0m\u001b[0;34m)\u001b[0m\u001b[0;34m\u001b[0m\u001b[0;34m\u001b[0m\u001b[0m\n\u001b[1;32m    336\u001b[0m             \u001b[0;32melif\u001b[0m \u001b[0mop\u001b[0m \u001b[0;32min\u001b[0m \u001b[0mhascompare\u001b[0m\u001b[0;34m:\u001b[0m\u001b[0;34m\u001b[0m\u001b[0;34m\u001b[0m\u001b[0m\n\u001b[0;32m--> 337\u001b[0;31m                 \u001b[0margval\u001b[0m \u001b[0;34m=\u001b[0m \u001b[0mcmp_op\u001b[0m\u001b[0;34m[\u001b[0m\u001b[0marg\u001b[0m\u001b[0;34m]\u001b[0m\u001b[0;34m\u001b[0m\u001b[0;34m\u001b[0m\u001b[0m\n\u001b[0m\u001b[1;32m    338\u001b[0m                 \u001b[0margrepr\u001b[0m \u001b[0;34m=\u001b[0m \u001b[0margval\u001b[0m\u001b[0;34m\u001b[0m\u001b[0;34m\u001b[0m\u001b[0m\n\u001b[1;32m    339\u001b[0m             \u001b[0;32melif\u001b[0m \u001b[0mop\u001b[0m \u001b[0;32min\u001b[0m \u001b[0mhasfree\u001b[0m\u001b[0;34m:\u001b[0m\u001b[0;34m\u001b[0m\u001b[0;34m\u001b[0m\u001b[0m\n",
      "\u001b[0;31mIndexError\u001b[0m: tuple index out of range"
     ]
    }
   ],
   "source": [
    "import dis\n",
    "from glob import glob\n",
    "import os.path as op\n",
    "\n",
    "filename = op.join('/mnt/c/Users/since/Downloads','week_4.pyc')\n",
    "\n",
    "with open(filename, \"rb\") as file:\n",
    "#    magic = file.read(4)  # Read the magic number from the file\n",
    "#    timestamp = file.read(4)  # Read the timestamp from the file\n",
    "    code_object = file.read()  # Read the bytecode from the file\n",
    "\n",
    "dis.dis(code_object)\n"
   ]
  },
  {
   "cell_type": "code",
   "execution_count": null,
   "id": "1837261c-beb2-423b-bacd-acbaf791ce97",
   "metadata": {},
   "outputs": [],
   "source": []
  }
 ],
 "metadata": {
  "kernelspec": {
   "display_name": "Python 3 (ipykernel)",
   "language": "python",
   "name": "python3"
  },
  "language_info": {
   "codemirror_mode": {
    "name": "ipython",
    "version": 3
   },
   "file_extension": ".py",
   "mimetype": "text/x-python",
   "name": "python",
   "nbconvert_exporter": "python",
   "pygments_lexer": "ipython3",
   "version": "3.7.15"
  }
 },
 "nbformat": 4,
 "nbformat_minor": 5
}
